{
  "city": {
    "id": 2643743,
    "name": "London",
    "coord": {
      "lat": 51.5085,
      "lon": -0.1257
    },
    "country": "GB",
    "population": 0,
    "timezone": 3600,
    "sunrise": 1601878086,
    "sunset": 1601918957
  },
  "list": [
    {
      "dt": 1601920800,
      "main": {
        "temp": "15° C",
        "feels_like": "11° C",
        "temp_min": "14° C",
        "temp_max": "15° C",
        "pressure": 997,
        "sea_level": 997,
        "grnd_level": 995,
        "humidity": 66,
        "temp_kf": 1
      },
      "weather": [
        {
          "id": 500,
          "main": "Rain",
          "description": "light rain",
          "icon": "10n"
        }
      ],
      "clouds": {
        "all": 69
      },
      "wind": {
        "speed": 6.32,
        "deg": 268
      },
      "visibility": 10000,
      "pop": 0.94,
      "rain": {
        "3h": 0.74
      },
      "sys": {
        "pod": "n"
      },
      "dt_txt": "2020-10-05 18:00",
      "light": false,
      "day": "day-0"
    },
    {
      "dt": 1601931600,
      "main": {
        "temp": "14° C",
        "feels_like": "9° C",
        "temp_min": "13° C",
        "temp_max": "14° C",
        "pressure": 998,
        "sea_level": 998,
        "grnd_level": 996,
        "humidity": 74,
        "temp_kf": 0.7
      },
      "weather": [
        {
          "id": 803,
          "main": "Clouds",
          "description": "broken clouds",
          "icon": "04n"
        }
      ],
      "clouds": {
        "all": 54
      },
      "wind": {
        "speed": 6.51,
        "deg": 250
      },
      "visibility": 10000,
      "pop": 0,
      "sys": {
        "pod": "n"
      },
      "dt_txt": "2020-10-05 21:00",
      "light": false,
      "day": "day-0"
    },
    {
      "dt": 1601942400,
      "main": {
        "temp": "12° C",
        "feels_like": "8° C",
        "temp_min": "12° C",
        "temp_max": "12° C",
        "pressure": 998,
        "sea_level": 998,
        "grnd_level": 995,
        "humidity": 77,
        "temp_kf": 0.28
      },
      "weather": [
        {
          "id": 500,
          "main": "Rain",
          "description": "light rain",
          "icon": "10n"
        }
      ],
      "clouds": {
        "all": 68
      },
      "wind": {
        "speed": 4.77,
        "deg": 228
      },
      "visibility": 10000,
      "pop": 0.24,
      "rain": {
        "3h": 0.31
      },
      "sys": {
        "pod": "n"
      },
      "dt_txt": "2020-10-06 00:00",
      "light": false,
      "day": "day-1"
    },
    {
      "dt": 1601953200,
      "main": {
        "temp": "13° C",
        "feels_like": "10° C",
        "temp_min": "13° C",
        "temp_max": "13° C",
        "pressure": 995,
        "sea_level": 995,
        "grnd_level": 993,
        "humidity": 85,
        "temp_kf": 0.03
      },
      "weather": [
        {
          "id": 500,
          "main": "Rain",
          "description": "light rain",
          "icon": "10n"
        }
      ],
      "clouds": {
        "all": 96
      },
      "wind": {
        "speed": 4.78,
        "deg": 225
      },
      "visibility": 10000,
      "pop": 0.88,
      "rain": {
        "3h": 0.78
      },
      "sys": {
        "pod": "n"
      },
      "dt_txt": "2020-10-06 03:00",
      "light": false,
      "day": "day-1"
    },
    {
      "dt": 1601964000,
      "main": {
        "temp": "12° C",
        "feels_like": "8° C",
        "temp_min": "12° C",
        "temp_max": "12° C",
        "pressure": 995,
        "sea_level": 995,
        "grnd_level": 992,
        "humidity": 79,
        "temp_kf": 0
      },
      "weather": [
        {
          "id": 500,
          "main": "Rain",
          "description": "light rain",
          "icon": "10n"
        }
      ],
      "clouds": {
        "all": 78
      },
      "wind": {
        "speed": 5.66,
        "deg": 251
      },
      "visibility": 10000,
      "pop": 0.82,
      "rain": {
        "3h": 0.13
      },
      "sys": {
        "pod": "n"
      },
      "dt_txt": "2020-10-06 06:00",
      "light": true,
      "day": "day-1"
    },
    {
      "dt": 1601974800,
      "main": {
        "temp": "14° C",
        "feels_like": "8° C",
        "temp_min": "14° C",
        "temp_max": "14° C",
        "pressure": 996,
        "sea_level": 996,
        "grnd_level": 993,
        "humidity": 68,
        "temp_kf": 0
      },
      "weather": [
        {
          "id": 500,
          "main": "Rain",
          "description": "light rain",
          "icon": "10d"
        }
      ],
      "clouds": {
        "all": 80
      },
      "wind": {
        "speed": 6.89,
        "deg": 256
      },
      "visibility": 10000,
      "pop": 0.38,
      "rain": {
        "3h": 0.31
      },
      "sys": {
        "pod": "d"
      },
      "dt_txt": "2020-10-06 09:00",
      "light": true,
      "day": "day-1"
    },
    {
      "dt": 1601985600,
      "main": {
        "temp": "15° C",
        "feels_like": "10° C",
        "temp_min": "15° C",
        "temp_max": "15° C",
        "pressure": 997,
        "sea_level": 997,
        "grnd_level": 994,
        "humidity": 57,
        "temp_kf": 0
      },
      "weather": [
        {
          "id": 500,
          "main": "Rain",
          "description": "light rain",
          "icon": "10d"
        }
      ],
      "clouds": {
        "all": 84
      },
      "wind": {
        "speed": 6.29,
        "deg": 255
      },
      "visibility": 10000,
      "pop": 0.9,
      "rain": {
        "3h": 0.36
      },
      "sys": {
        "pod": "d"
      },
      "dt_txt": "2020-10-06 12:00",
      "light": true,
      "day": "day-1"
    },
    {
      "dt": 1601996400,
      "main": {
        "temp": "14° C",
        "feels_like": "9° C",
        "temp_min": "14° C",
        "temp_max": "14° C",
        "pressure": 997,
        "sea_level": 997,
        "grnd_level": 994,
        "humidity": 63,
        "temp_kf": 0
      },
      "weather": [
        {
          "id": 500,
          "main": "Rain",
          "description": "light rain",
          "icon": "10d"
        }
      ],
      "clouds": {
        "all": 95
      },
      "wind": {
        "speed": 7.19,
        "deg": 252
      },
      "visibility": 10000,
      "pop": 0.94,
      "rain": {
        "3h": 0.54
      },
      "sys": {
        "pod": "d"
      },
      "dt_txt": "2020-10-06 15:00",
      "light": true,
      "day": "day-1"
    },
    {
      "dt": 1602007200,
      "main": {
        "temp": "14° C",
        "feels_like": "9° C",
        "temp_min": "14° C",
        "temp_max": "14° C",
        "pressure": 998,
        "sea_level": 998,
        "grnd_level": 995,
        "humidity": 68,
        "temp_kf": 0
      },
      "weather": [
        {
          "id": 500,
          "main": "Rain",
          "description": "light rain",
          "icon": "10n"
        }
      ],
      "clouds": {
        "all": 90
      },
      "wind": {
        "speed": 6.21,
        "deg": 266
      },
      "visibility": 10000,
      "pop": 0.79,
      "rain": {
        "3h": 0.56
      },
      "sys": {
        "pod": "n"
      },
      "dt_txt": "2020-10-06 18:00",
      "light": false,
      "day": "day-1"
    },
    {
      "dt": 1602018000,
      "main": {
        "temp": "13° C",
        "feels_like": "8° C",
        "temp_min": "13° C",
        "temp_max": "13° C",
        "pressure": 1001,
        "sea_level": 1001,
        "grnd_level": 998,
        "humidity": 71,
        "temp_kf": 0
      },
      "weather": [
        {
          "id": 802,
          "main": "Clouds",
          "description": "scattered clouds",
          "icon": "03n"
        }
      ],
      "clouds": {
        "all": 28
      },
      "wind": {
        "speed": 6.19,
        "deg": 276
      },
      "visibility": 10000,
      "pop": 0,
      "sys": {
        "pod": "n"
      },
      "dt_txt": "2020-10-06 21:00",
      "light": false,
      "day": "day-1"
    },
    {
      "dt": 1602028800,
      "main": {
        "temp": "12° C",
        "feels_like": "7° C",
        "temp_min": "12° C",
        "temp_max": "12° C",
        "pressure": 1003,
        "sea_level": 1003,
        "grnd_level": 1001,
        "humidity": 73,
        "temp_kf": 0
      },
      "weather": [
        {
          "id": 803,
          "main": "Clouds",
          "description": "broken clouds",
          "icon": "04n"
        }
      ],
      "clouds": {
        "all": 58
      },
      "wind": {
        "speed": 6.25,
        "deg": 277
      },
      "visibility": 10000,
      "pop": 0,
      "sys": {
        "pod": "n"
      },
      "dt_txt": "2020-10-07 00:00",
      "light": false,
      "day": "day-2"
    },
    {
      "dt": 1602039600,
      "main": {
        "temp": "12° C",
        "feels_like": "7° C",
        "temp_min": "12° C",
        "temp_max": "12° C",
        "pressure": 1006,
        "sea_level": 1006,
        "grnd_level": 1003,
        "humidity": 76,
        "temp_kf": 0
      },
      "weather": [
        {
          "id": 802,
          "main": "Clouds",
          "description": "scattered clouds",
          "icon": "03n"
        }
      ],
      "clouds": {
        "all": 40
      },
      "wind": {
        "speed": 5.94,
        "deg": 281
      },
      "visibility": 10000,
      "pop": 0,
      "sys": {
        "pod": "n"
      },
      "dt_txt": "2020-10-07 03:00",
      "light": false,
      "day": "day-2"
    },
    {
      "dt": 1602050400,
      "main": {
        "temp": "11° C",
        "feels_like": "6° C",
        "temp_min": "11° C",
        "temp_max": "11° C",
        "pressure": 1009,
        "sea_level": 1009,
        "grnd_level": 1006,
        "humidity": 72,
        "temp_kf": 0
      },
      "weather": [
        {
          "id": 500,
          "main": "Rain",
          "description": "light rain",
          "icon": "10n"
        }
      ],
      "clouds": {
        "all": 68
      },
      "wind": {
        "speed": 5.9,
        "deg": 282
      },
      "visibility": 10000,
      "pop": 0.2,
      "rain": {
        "3h": 0.12
      },
      "sys": {
        "pod": "n"
      },
      "dt_txt": "2020-10-07 06:00",
      "light": true,
      "day": "day-2"
    },
    {
      "dt": 1602061200,
      "main": {
        "temp": "12° C",
        "feels_like": "7° C",
        "temp_min": "12° C",
        "temp_max": "12° C",
        "pressure": 1012,
        "sea_level": 1012,
        "grnd_level": 1009,
        "humidity": 64,
        "temp_kf": 0
      },
      "weather": [
        {
          "id": 804,
          "main": "Clouds",
          "description": "overcast clouds",
          "icon": "04d"
        }
      ],
      "clouds": {
        "all": 100
      },
      "wind": {
        "speed": 5.71,
        "deg": 282
      },
      "visibility": 10000,
      "pop": 0,
      "sys": {
        "pod": "d"
      },
      "dt_txt": "2020-10-07 09:00",
      "light": true,
      "day": "day-2"
    },
    {
      "dt": 1602072000,
      "main": {
        "temp": "14° C",
        "feels_like": "9° C",
        "temp_min": "14° C",
        "temp_max": "14° C",
        "pressure": 1014,
        "sea_level": 1014,
        "grnd_level": 1011,
        "humidity": 54,
        "temp_kf": 0
      },
      "weather": [
        {
          "id": 803,
          "main": "Clouds",
          "description": "broken clouds",
          "icon": "04d"
        }
      ],
      "clouds": {
        "all": 70
      },
      "wind": {
        "speed": 5.32,
        "deg": 274
      },
      "visibility": 10000,
      "pop": 0,
      "sys": {
        "pod": "d"
      },
      "dt_txt": "2020-10-07 12:00",
      "light": true,
      "day": "day-2"
    },
    {
      "dt": 1602082800,
      "main": {
        "temp": "15° C",
        "feels_like": "10° C",
        "temp_min": "15° C",
        "temp_max": "15° C",
        "pressure": 1014,
        "sea_level": 1014,
        "grnd_level": 1012,
        "humidity": 53,
        "temp_kf": 0
      },
      "weather": [
        {
          "id": 801,
          "main": "Clouds",
          "description": "few clouds",
          "icon": "02d"
        }
      ],
      "clouds": {
        "all": 19
      },
      "wind": {
        "speed": 5.46,
        "deg": 260
      },
      "visibility": 10000,
      "pop": 0,
      "sys": {
        "pod": "d"
      },
      "dt_txt": "2020-10-07 15:00",
      "light": true,
      "day": "day-2"
    },
    {
      "dt": 1602093600,
      "main": {
        "temp": "13° C",
        "feels_like": "10° C",
        "temp_min": "13° C",
        "temp_max": "13° C",
        "pressure": 1014,
        "sea_level": 1014,
        "grnd_level": 1011,
        "humidity": 65,
        "temp_kf": 0
      },
      "weather": [
        {
          "id": 803,
          "main": "Clouds",
          "description": "broken clouds",
          "icon": "04n"
        }
      ],
      "clouds": {
        "all": 54
      },
      "wind": {
        "speed": 3.56,
        "deg": 235
      },
      "visibility": 10000,
      "pop": 0,
      "sys": {
        "pod": "n"
      },
      "dt_txt": "2020-10-07 18:00",
      "light": false,
      "day": "day-2"
    },
    {
      "dt": 1602104400,
      "main": {
        "temp": "13° C",
        "feels_like": "10° C",
        "temp_min": "13° C",
        "temp_max": "13° C",
        "pressure": 1014,
        "sea_level": 1014,
        "grnd_level": 1012,
        "humidity": 76,
        "temp_kf": 0
      },
      "weather": [
        {
          "id": 500,
          "main": "Rain",
          "description": "light rain",
          "icon": "10n"
        }
      ],
      "clouds": {
        "all": 100
      },
      "wind": {
        "speed": 3.39,
        "deg": 218
      },
      "visibility": 10000,
      "pop": 0.38,
      "rain": {
        "3h": 0.25
      },
      "sys": {
        "pod": "n"
      },
      "dt_txt": "2020-10-07 21:00",
      "light": false,
      "day": "day-2"
    },
    {
      "dt": 1602115200,
      "main": {
        "temp": "12° C",
        "feels_like": "11° C",
        "temp_min": "12° C",
        "temp_max": "12° C",
        "pressure": 1012,
        "sea_level": 1012,
        "grnd_level": 1010,
        "humidity": 85,
        "temp_kf": 0
      },
      "weather": [
        {
          "id": 500,
          "main": "Rain",
          "description": "light rain",
          "icon": "10n"
        }
      ],
      "clouds": {
        "all": 100
      },
      "wind": {
        "speed": 1.29,
        "deg": 214
      },
      "visibility": 9299,
      "pop": 1,
      "rain": {
        "3h": 1.66
      },
      "sys": {
        "pod": "n"
      },
      "dt_txt": "2020-10-08 00:00",
      "light": false,
      "day": "day-3"
    },
    {
      "dt": 1602126000,
      "main": {
        "temp": "12° C",
        "feels_like": "11° C",
        "temp_min": "12° C",
        "temp_max": "12° C",
        "pressure": 1011,
        "sea_level": 1011,
        "grnd_level": 1008,
        "humidity": 86,
        "temp_kf": 0
      },
      "weather": [
        {
          "id": 500,
          "main": "Rain",
          "description": "light rain",
          "icon": "10n"
        }
      ],
      "clouds": {
        "all": 100
      },
      "wind": {
        "speed": 1.82,
        "deg": 67
      },
      "visibility": 10000,
      "pop": 1,
      "rain": {
        "3h": 1.78
      },
      "sys": {
        "pod": "n"
      },
      "dt_txt": "2020-10-08 03:00",
      "light": false,
      "day": "day-3"
    },
    {
      "dt": 1602136800,
      "main": {
        "temp": "12° C",
        "feels_like": "10° C",
        "temp_min": "12° C",
        "temp_max": "12° C",
        "pressure": 1011,
        "sea_level": 1011,
        "grnd_level": 1008,
        "humidity": 87,
        "temp_kf": 0
      },
      "weather": [
        {
          "id": 500,
          "main": "Rain",
          "description": "light rain",
          "icon": "10n"
        }
      ],
      "clouds": {
        "all": 100
      },
      "wind": {
        "speed": 2.12,
        "deg": 63
      },
      "visibility": 10000,
      "pop": 1,
      "rain": {
        "3h": 1.77
      },
      "sys": {
        "pod": "n"
      },
      "dt_txt": "2020-10-08 06:00",
      "light": true,
      "day": "day-3"
    },
    {
      "dt": 1602147600,
      "main": {
        "temp": "12° C",
        "feels_like": "11° C",
        "temp_min": "12° C",
        "temp_max": "12° C",
        "pressure": 1011,
        "sea_level": 1011,
        "grnd_level": 1009,
        "humidity": 91,
        "temp_kf": 0
      },
      "weather": [
        {
          "id": 501,
          "main": "Rain",
          "description": "moderate rain",
          "icon": "10d"
        }
      ],
      "clouds": {
        "all": 100
      },
      "wind": {
        "speed": 2.07,
        "deg": 79
      },
      "visibility": 6748,
      "pop": 1,
      "rain": {
        "3h": 5.45
      },
      "sys": {
        "pod": "d"
      },
      "dt_txt": "2020-10-08 09:00",
      "light": true,
      "day": "day-3"
    },
    {
      "dt": 1602158400,
      "main": {
        "temp": "13° C",
        "feels_like": "12° C",
        "temp_min": "13° C",
        "temp_max": "13° C",
        "pressure": 1012,
        "sea_level": 1012,
        "grnd_level": 1009,
        "humidity": 89,
        "temp_kf": 0
      },
      "weather": [
        {
          "id": 500,
          "main": "Rain",
          "description": "light rain",
          "icon": "10d"
        }
      ],
      "clouds": {
        "all": 100
      },
      "wind": {
        "speed": 1.86,
        "deg": 26
      },
      "visibility": 10000,
      "pop": 1,
      "rain": {
        "3h": 1.51
      },
      "sys": {
        "pod": "d"
      },
      "dt_txt": "2020-10-08 12:00",
      "light": true,
      "day": "day-3"
    },
    {
      "dt": 1602169200,
      "main": {
        "temp": "13° C",
        "feels_like": "12° C",
        "temp_min": "13° C",
        "temp_max": "13° C",
        "pressure": 1012,
        "sea_level": 1012,
        "grnd_level": 1010,
        "humidity": 86,
        "temp_kf": 0
      },
      "weather": [
        {
          "id": 804,
          "main": "Clouds",
          "description": "overcast clouds",
          "icon": "04d"
        }
      ],
      "clouds": {
        "all": 100
      },
      "wind": {
        "speed": 1.52,
        "deg": 7
      },
      "visibility": 10000,
      "pop": 0.25,
      "sys": {
        "pod": "d"
      },
      "dt_txt": "2020-10-08 15:00",
      "light": true,
      "day": "day-3"
    },
    {
      "dt": 1602180000,
      "main": {
        "temp": "13° C",
        "feels_like": "12° C",
        "temp_min": "13° C",
        "temp_max": "13° C",
        "pressure": 1013,
        "sea_level": 1013,
        "grnd_level": 1010,
        "humidity": 85,
        "temp_kf": 0
      },
      "weather": [
        {
          "id": 804,
          "main": "Clouds",
          "description": "overcast clouds",
          "icon": "04n"
        }
      ],
      "clouds": {
        "all": 100
      },
      "wind": {
        "speed": 0.6,
        "deg": 37
      },
      "visibility": 10000,
      "pop": 0.21,
      "sys": {
        "pod": "n"
      },
      "dt_txt": "2020-10-08 18:00",
      "light": false,
      "day": "day-3"
    },
    {
      "dt": 1602190800,
      "main": {
        "temp": "13° C",
        "feels_like": "12° C",
        "temp_min": "13° C",
        "temp_max": "13° C",
        "pressure": 1014,
        "sea_level": 1014,
        "grnd_level": 1011,
        "humidity": 87,
        "temp_kf": 0
      },
      "weather": [
        {
          "id": 500,
          "main": "Rain",
          "description": "light rain",
          "icon": "10n"
        }
      ],
      "clouds": {
        "all": 100
      },
      "wind": {
        "speed": 0.72,
        "deg": 184
      },
      "visibility": 10000,
      "pop": 0.22,
      "rain": {
        "3h": 0.12
      },
      "sys": {
        "pod": "n"
      },
      "dt_txt": "2020-10-08 21:00",
      "light": false,
      "day": "day-3"
    },
    {
      "dt": 1602201600,
      "main": {
        "temp": "13° C",
        "feels_like": "12° C",
        "temp_min": "13° C",
        "temp_max": "13° C",
        "pressure": 1012,
        "sea_level": 1012,
        "grnd_level": 1009,
        "humidity": 88,
        "temp_kf": 0
      },
      "weather": [
        {
          "id": 804,
          "main": "Clouds",
          "description": "overcast clouds",
          "icon": "04n"
        }
      ],
      "clouds": {
        "all": 100
      },
      "wind": {
        "speed": 1.63,
        "deg": 144
      },
      "visibility": 10000,
      "pop": 0.21,
      "sys": {
        "pod": "n"
      },
      "dt_txt": "2020-10-09 00:00",
      "light": false,
      "day": "day-4"
    },
    {
      "dt": 1602212400,
      "main": {
        "temp": "13° C",
        "feels_like": "12° C",
        "temp_min": "13° C",
        "temp_max": "13° C",
        "pressure": 1010,
        "sea_level": 1010,
        "grnd_level": 1007,
        "humidity": 95,
        "temp_kf": 0
      },
      "weather": [
        {
          "id": 501,
          "main": "Rain",
          "description": "moderate rain",
          "icon": "10n"
        }
      ],
      "clouds": {
        "all": 100
      },
      "wind": {
        "speed": 2.52,
        "deg": 147
      },
      "visibility": 5177,
      "pop": 1,
      "rain": {
        "3h": 6.47
      },
      "sys": {
        "pod": "n"
      },
      "dt_txt": "2020-10-09 03:00",
      "light": false,
      "day": "day-4"
    },
    {
      "dt": 1602223200,
      "main": {
        "temp": "15° C",
        "feels_like": "12° C",
        "temp_min": "15° C",
        "temp_max": "15° C",
        "pressure": 1008,
        "sea_level": 1008,
        "grnd_level": 1005,
        "humidity": 88,
        "temp_kf": 0
      },
      "weather": [
        {
          "id": 501,
          "main": "Rain",
          "description": "moderate rain",
          "icon": "10n"
        }
      ],
      "clouds": {
        "all": 100
      },
      "wind": {
        "speed": 6.79,
        "deg": 223
      },
      "visibility": 9405,
      "pop": 1,
      "rain": {
        "3h": 6.11
      },
      "sys": {
        "pod": "n"
      },
      "dt_txt": "2020-10-09 06:00",
      "light": true,
      "day": "day-4"
    },
    {
      "dt": 1602234000,
      "main": {
        "temp": "15° C",
        "feels_like": "12° C",
        "temp_min": "15° C",
        "temp_max": "15° C",
        "pressure": 1008,
        "sea_level": 1008,
        "grnd_level": 1005,
        "humidity": 90,
        "temp_kf": 0
      },
      "weather": [
        {
          "id": 501,
          "main": "Rain",
          "description": "moderate rain",
          "icon": "10d"
        }
      ],
      "clouds": {
        "all": 100
      },
      "wind": {
        "speed": 4.38,
        "deg": 277
      },
      "visibility": 6982,
      "pop": 1,
      "rain": {
        "3h": 7.59
      },
      "sys": {
        "pod": "d"
      },
      "dt_txt": "2020-10-09 09:00",
      "light": true,
      "day": "day-4"
    },
    {
      "dt": 1602244800,
      "main": {
        "temp": "12° C",
        "feels_like": "8° C",
        "temp_min": "12° C",
        "temp_max": "12° C",
        "pressure": 1009,
        "sea_level": 1009,
        "grnd_level": 1007,
        "humidity": 77,
        "temp_kf": 0
      },
      "weather": [
        {
          "id": 501,
          "main": "Rain",
          "description": "moderate rain",
          "icon": "10d"
        }
      ],
      "clouds": {
        "all": 100
      },
      "wind": {
        "speed": 5.07,
        "deg": 328
      },
      "visibility": 10000,
      "pop": 1,
      "rain": {
        "3h": 5.55
      },
      "sys": {
        "pod": "d"
      },
      "dt_txt": "2020-10-09 12:00",
      "light": true,
      "day": "day-4"
    },
    {
      "dt": 1602255600,
      "main": {
        "temp": "14° C",
        "feels_like": "9° C",
        "temp_min": "14° C",
        "temp_max": "14° C",
        "pressure": 1011,
        "sea_level": 1011,
        "grnd_level": 1008,
        "humidity": 53,
        "temp_kf": 0
      },
      "weather": [
        {
          "id": 803,
          "main": "Clouds",
          "description": "broken clouds",
          "icon": "04d"
        }
      ],
      "clouds": {
        "all": 66
      },
      "wind": {
        "speed": 4.52,
        "deg": 321
      },
      "visibility": 10000,
      "pop": 0.06,
      "sys": {
        "pod": "d"
      },
      "dt_txt": "2020-10-09 15:00",
      "light": true,
      "day": "day-4"
    },
    {
      "dt": 1602266400,
      "main": {
        "temp": "12° C",
        "feels_like": "9° C",
        "temp_min": "12° C",
        "temp_max": "12° C",
        "pressure": 1014,
        "sea_level": 1014,
        "grnd_level": 1011,
        "humidity": 64,
        "temp_kf": 0
      },
      "weather": [
        {
          "id": 802,
          "main": "Clouds",
          "description": "scattered clouds",
          "icon": "03n"
        }
      ],
      "clouds": {
        "all": 33
      },
      "wind": {
        "speed": 2.93,
        "deg": 290
      },
      "visibility": 10000,
      "pop": 0.06,
      "sys": {
        "pod": "n"
      },
      "dt_txt": "2020-10-09 18:00",
      "light": false,
      "day": "day-4"
    },
    {
      "dt": 1602277200,
      "main": {
        "temp": "10° C",
        "feels_like": "6° C",
        "temp_min": "10° C",
        "temp_max": "10° C",
        "pressure": 1016,
        "sea_level": 1016,
        "grnd_level": 1013,
        "humidity": 67,
        "temp_kf": 0
      },
      "weather": [
        {
          "id": 800,
          "main": "Clear",
          "description": "clear sky",
          "icon": "01n"
        }
      ],
      "clouds": {
        "all": 1
      },
      "wind": {
        "speed": 4.38,
        "deg": 290
      },
      "visibility": 10000,
      "pop": 0,
      "sys": {
        "pod": "n"
      },
      "dt_txt": "2020-10-09 21:00",
      "light": false,
      "day": "day-4"
    },
    {
      "dt": 1602288000,
      "main": {
        "temp": "9° C",
        "feels_like": "5° C",
        "temp_min": "9° C",
        "temp_max": "9° C",
        "pressure": 1016,
        "sea_level": 1016,
        "grnd_level": 1013,
        "humidity": 65,
        "temp_kf": 0
      },
      "weather": [
        {
          "id": 800,
          "main": "Clear",
          "description": "clear sky",
          "icon": "01n"
        }
      ],
      "clouds": {
        "all": 0
      },
      "wind": {
        "speed": 4.18,
        "deg": 264
      },
      "visibility": 10000,
      "pop": 0,
      "sys": {
        "pod": "n"
      },
      "dt_txt": "2020-10-10 00:00",
      "light": false,
      "day": "day-5"
    },
    {
      "dt": 1602298800,
      "main": {
        "temp": "9° C",
        "feels_like": "4° C",
        "temp_min": "9° C",
        "temp_max": "9° C",
        "pressure": 1016,
        "sea_level": 1016,
        "grnd_level": 1013,
        "humidity": 69,
        "temp_kf": 0
      },
      "weather": [
        {
          "id": 800,
          "main": "Clear",
          "description": "clear sky",
          "icon": "01n"
        }
      ],
      "clouds": {
        "all": 0
      },
      "wind": {
        "speed": 4.93,
        "deg": 257
      },
      "visibility": 10000,
      "pop": 0,
      "sys": {
        "pod": "n"
      },
      "dt_txt": "2020-10-10 03:00",
      "light": false,
      "day": "day-5"
    },
    {
      "dt": 1602309600,
      "main": {
        "temp": "9° C",
        "feels_like": "4° C",
        "temp_min": "9° C",
        "temp_max": "9° C",
        "pressure": 1016,
        "sea_level": 1016,
        "grnd_level": 1014,
        "humidity": 77,
        "temp_kf": 0
      },
      "weather": [
        {
          "id": 801,
          "main": "Clouds",
          "description": "few clouds",
          "icon": "02n"
        }
      ],
      "clouds": {
        "all": 22
      },
      "wind": {
        "speed": 5.1,
        "deg": 265
      },
      "visibility": 10000,
      "pop": 0,
      "sys": {
        "pod": "n"
      },
      "dt_txt": "2020-10-10 06:00",
      "light": true,
      "day": "day-5"
    },
    {
      "dt": 1602320400,
      "main": {
        "temp": "11° C",
        "feels_like": "5° C",
        "temp_min": "11° C",
        "temp_max": "11° C",
        "pressure": 1017,
        "sea_level": 1017,
        "grnd_level": 1014,
        "humidity": 61,
        "temp_kf": 0
      },
      "weather": [
        {
          "id": 802,
          "main": "Clouds",
          "description": "scattered clouds",
          "icon": "03d"
        }
      ],
      "clouds": {
        "all": 38
      },
      "wind": {
        "speed": 5.73,
        "deg": 288
      },
      "visibility": 10000,
      "pop": 0,
      "sys": {
        "pod": "d"
      },
      "dt_txt": "2020-10-10 09:00",
      "light": true,
      "day": "day-5"
    },
    {
      "dt": 1602331200,
      "main": {
        "temp": "13° C",
        "feels_like": "7° C",
        "temp_min": "13° C",
        "temp_max": "13° C",
        "pressure": 1018,
        "sea_level": 1018,
        "grnd_level": 1015,
        "humidity": 52,
        "temp_kf": 0
      },
      "weather": [
        {
          "id": 801,
          "main": "Clouds",
          "description": "few clouds",
          "icon": "02d"
        }
      ],
      "clouds": {
        "all": 18
      },
      "wind": {
        "speed": 6.36,
        "deg": 287
      },
      "visibility": 10000,
      "pop": 0,
      "sys": {
        "pod": "d"
      },
      "dt_txt": "2020-10-10 12:00",
      "light": true,
      "day": "day-5"
    },
    {
      "dt": 1602342000,
      "main": {
        "temp": "13° C",
        "feels_like": "7° C",
        "temp_min": "13° C",
        "temp_max": "13° C",
        "pressure": 1018,
        "sea_level": 1018,
        "grnd_level": 1015,
        "humidity": 49,
        "temp_kf": 0
      },
      "weather": [
        {
          "id": 802,
          "main": "Clouds",
          "description": "scattered clouds",
          "icon": "03d"
        }
      ],
      "clouds": {
        "all": 38
      },
      "wind": {
        "speed": 6.64,
        "deg": 293
      },
      "visibility": 10000,
      "pop": 0,
      "sys": {
        "pod": "d"
      },
      "dt_txt": "2020-10-10 15:00",
      "light": true,
      "day": "day-5"
    }
  ]
}
